CHANGES
LICENSE.GPL
LICENSE.txt
README.txt
setup.cfg
setup.py
Products/__init__.py
Products.croppingimage.egg-info/PKG-INFO
Products.croppingimage.egg-info/SOURCES.txt
Products.croppingimage.egg-info/dependency_links.txt
Products.croppingimage.egg-info/entry_points.txt
Products.croppingimage.egg-info/namespace_packages.txt
Products.croppingimage.egg-info/not-zip-safe
Products.croppingimage.egg-info/requires.txt
Products.croppingimage.egg-info/top_level.txt
Products/croppingimage/README.txt
Products/croppingimage/__init__.py
Products/croppingimage/config.py
Products/croppingimage/configure.zcml
Products/croppingimage/croppingimage.py
Products/croppingimage/field.py
Products/croppingimage/permissions.py
Products/croppingimage/schema.py
Products/croppingimage/version.txt
Products/croppingimage/Extensions/Install.py
Products/croppingimage/skins/croppingimage/README.txt
docs/examples.html
docs/examples.txt
docs/img/result-landscape-force-format.jpg
docs/img/result-landscape.jpg
docs/img/result-portrait-force-format.jpg
docs/img/result-portrait.jpg