Metadata-Version: 1.0
Name: Products.croppingimage
Version: 0.2rc2
Summary: ImageField that crops images that do not fit the expected ratio
Home-page: http://plone.org/products/cropping-imagefield
Author: Ben Mason
Author-email: ben@sharkbyte.co.uk
License: GPL
Platform: UNKNOWN
Classifier: Framework :: Plone
Classifier: Framework :: Zope2
Classifier: Programming Language :: Python
Classifier: Topic :: Software Development :: Libraries :: Python Modules
